getcontents/__init__.py
getcontents/http_client.py
getcontents/response.py
getcontents/utils.py
getcontents-0.0.0.dist-info/LICENSE
getcontents-0.0.0.dist-info/METADATA
getcontents-0.0.0.dist-info/WHEEL
getcontents-0.0.0.dist-info/top_level.txt
getcontents-0.0.0.dist-info/RECORD
