Metadata-Version: 2.1
Name: getcontents
Version: 0.0.0
Summary: A minimal HTTP/1.x client that is only used to deal with APIs. It is not designed to be bulletproof or full-featured like requests.
Home-page: https://github.com/nggit/getcontents
Author: nggit
Author-email: contact@anggit.com
License: MIT
Classifier: Development Status :: 3 - Alpha
Classifier: License :: OSI Approved :: MIT License
Classifier: Operating System :: OS Independent
Classifier: Topic :: Internet :: WWW/HTTP
Classifier: Topic :: Software Development :: Libraries
License-File: LICENSE
